{"id":"CYZvsAv9dRoWzEflWaae4","title":"Parametric Hermeneutics","vault":{"fsPath":"placecolor","remote":{"type":"git","url":"https://github.com/SR--/placecolor.git"},"name":"placecolor"},"type":"note","desc":"","links":[{"type":"ref","from":{"fname":"experiment.parametric-hermeneutics","id":"CYZvsAv9dRoWzEflWaae4","vaultName":"placecolor"},"value":"admin.template.experiment","position":{"start":{"line":7,"column":1,"offset":184},"end":{"line":7,"column":31,"offset":214},"indent":[]},"xvault":false,"to":{"fname":"admin.template.experiment"}},{"from":{"fname":"experiment","vaultName":"placecolor"},"type":"backlink","position":{"start":{"line":13,"column":3,"offset":433},"end":{"line":13,"column":65,"offset":495},"indent":[]},"value":"experiment.parametric-hermeneutics"}],"anchors":{"project-description":{"type":"header","text":"Project Description","value":"project-description","line":14,"column":0},"context":{"type":"header","text":"Context","value":"context","line":16,"column":0},"objectives":{"type":"header","text":"Objectives","value":"objectives","line":18,"column":0},"agents":{"type":"header","text":"Agents","value":"agents","line":20,"column":0},"methods":{"type":"header","text":"Methods","value":"methods","line":22,"column":0},"results":{"type":"header","text":"Results","value":"results","line":24,"column":0},"discussion":{"type":"header","text":"Discussion","value":"discussion","line":26,"column":0},"notes":{"type":"header","text":"Notes","value":"notes","line":28,"column":0},"smart-spaces":{"type":"header","text":"Smart Spaces","value":"smart-spaces","line":30,"column":0},"machine-learning":{"type":"header","text":"Machine Learning","value":"machine-learning","line":37,"column":0}},"fname":"experiment.parametric-hermeneutics","updated":1625021121277,"created":1625021121277,"parent":"D7128jwSvEVrDT7EBiIq8","children":[],"data":{},"contentHash":"398e0af2092b59e9f6526c8ab8d1239d","custom":{}}
