{"id":"h8eNO16MFkDAD9s8wvhsw","title":"Human Perception of Color","vault":{"fsPath":"placecolor","remote":{"type":"git","url":"https://github.com/SR--/placecolor.git"},"name":"placecolor"},"type":"note","desc":"","links":[{"type":"wiki","from":{"fname":"relationship.color.perception.human","id":"h8eNO16MFkDAD9s8wvhsw","vaultName":"placecolor"},"value":"relationship.color.physics","alias":"relationship.color.physics","position":{"start":{"line":9,"column":3,"offset":339},"end":{"line":9,"column":33,"offset":369},"indent":[]},"xvault":false,"sameFile":false,"to":{"fname":"relationship.color.physics"}},{"type":"ref","from":{"fname":"relationship.color.perception.human","id":"h8eNO16MFkDAD9s8wvhsw","vaultName":"placecolor"},"value":"example.color-wavelength","position":{"start":{"line":5,"column":1,"offset":200},"end":{"line":5,"column":30,"offset":229},"indent":[]},"xvault":false,"to":{"fname":"example.color-wavelength"}},{"from":{"fname":"relationship.color.perception","vaultName":"placecolor"},"type":"backlink","position":{"start":{"line":7,"column":1,"offset":530},"end":{"line":7,"column":40,"offset":569},"indent":[]},"value":"relationship.color.perception.human"}],"anchors":{"differences-in-perceptual-ability-between-humans":{"type":"header","text":"Differences in perceptual ability between humans","value":"differences-in-perceptual-ability-between-humans","line":17,"column":0},"the-concept-of-colour-universals":{"type":"header","text":"The concept of colour universals","value":"the-concept-of-colour-universals","line":21,"column":0}},"fname":"relationship.color.perception.human","updated":1624928750239,"created":1624453472853,"parent":"8IHvmKLYA_wHaf2i5ISb9","children":[],"data":{},"contentHash":"68a647e2c3ff984f06c4b3691077b30f","custom":{}}
